erc20transfer/__init__.py
erc20transfer/erc20_abi.json
erc20transfer/erc20transfer.py
erc20transfer/__pycache__/__init__.cpython-39.pyc
erc20transfer/__pycache__/erc20transfer.cpython-39.pyc
caaj_evm-0.1.8.dist-info/METADATA
caaj_evm-0.1.8.dist-info/WHEEL
caaj_evm-0.1.8.dist-info/top_level.txt
caaj_evm-0.1.8.dist-info/RECORD
